{"uuids": {"phone_id": "95c09c45-adce-432a-a141-b96748dbbba2", "uuid": "0c8efd79-67ad-4649-8c5d-510a218ad4f9", "client_session_id": "8b76cae1-5164-45b3-9e6d-8c14b6898241", "advertising_id": "63a4bbf9-c2a4-469f-8118-282ec3a799c2", "device_id": "android-058c0ee5ee59d666"}, "cookie": {"csrftoken": "1jV6KqZOtTj8f7q6xLjQ7035BMdGIrvk", "ds_user_id": "40332789664", "ig_direct_region_hint": "ASH", "mid": "YIVOOgABAAHzT8ucVWq4INzd7gc6", "rur": "VLL", "sessionid": "40332789664%3ADjfjAty42EteYF%3A16", "shbid": "759", "shbts": "1619349053.2329574"}, "timing_value": {"last_login": 1619349053.127642, "last_experiments": 1619349053.127693}, "device_settings": {"app_version": "117.0.0.28.123", "android_version": "28", "android_release": "9.0", "dpi": "420dpi", "resolution": "1080x1920", "manufacturer": "OnePlus", "device": "ONEPLUS A3003", "model": "OnePlus3", "cpu": "qcom", "version_code": "180322800"}, "user_agent": "Instagram 117.0.0.28.123 Android (28/9.0; 420dpi; 1080x1920; OnePlus; ONEPLUS A3003; OnePlus3; qcom; en_US; 180322800)"}